[
  {
    "sn": "34958/544160",
    "ab": "cinpitu",
    "ch": "七點",
    "en": "",
    "img": "",
    "snd": true
  },
  {
    "sn": "34958/544161",
    "ab": "pasnanavaan",
    "ch": "學校",
    "en": "",
    "img": "",
    "snd": true
  },
  {
    "sn": "34958/544162",
    "ab": "masnanava",
    "ch": "老師",
    "en": "",
    "img": "",
    "snd": true
  },
  {
    "sn": "34958/544163",
    "ab": "aluszangan",
    "ch": "同學",
    "en": "",
    "img": "",
    "snd": true
  },
  {
    "sn": "34958/544164",
    "ab": "malisBunun",
    "ch": "族語",
    "en": "",
    "img": "",
    "snd": true
  },
  {
    "sn": "34958/544165",
    "ab": "minduldul",
    "ch": "起立",
    "en": "",
    "img": "",
    "snd": true
  },
  {
    "sn": "34958/544166",
    "ab": "pissauk",
    "ch": "敬禮",
    "en": "",
    "img": "",
    "snd": true
  },
  {
    "sn": "34958/544167",
    "ab": "isnavaan",
    "ch": "上課/上學",
    "en": "",
    "img": "",
    "snd": true
  },
  {
    "sn": "34958/544169",
    "ab": "issisipul",
    "ch": "數字",
    "en": "",
    "img": "",
    "snd": true
  },
  {
    "sn": "34958/544170",
    "ab": "huzas",
    "ch": "歌",
    "en": "",
    "img": "",
    "snd": true
  }
]