[
  {
    "sn": "35165/547369",
    "ab": "a ku gakku i ljaqedi ta niamen a umaq djemavac aken a ljemitaqadaw a magakku djemavac aken uta sematjumaq.",
    "ch": "我的學校在我們家旁邊，我天天走路去學校，也走路回家。",
    "en": "My school is next to our house, I walk to school every day, and I also walk home.",
    "img": "img/33763/525587.jpg",
    "snd": true
  },
  {
    "sn": "35165/547370",
    "ab": "inika kudral a nia gakku inika tjuruvu a situ na makakeljang amen a mapuljat.",
    "ch": "我們學校不大，沒有很多學生，大家互相認識。",
    "en": "Our school is not big, there are not many students, everyone knows each other.",
    "img": "img/33763/525588.jpg",
    "snd": true
  },
  {
    "sn": "35165/547371",
    "ab": "matevetevelj a kakedryan i undudju meseljang a kivangavang a maljavar.",
    "ch": "所有小朋友會聚在操場，一起玩球、一起聊天。",
    "en": "All the children will gather in the playground, play ball and chat together.",
    "img": "img/33763/525589.jpg",
    "snd": true
  },
  {
    "sn": "35165/547372",
    "ab": "kiseljang uta tiasinsi tjanuamen a kivangavang a gakku namaya ta qaca a tacemekeljan.",
    "ch": "老師們也會和我們一起玩，學校是個大家庭。",
    "en": "The teachers also play with us, the school is one big family.",
    "img": "img/33763/525590.jpg",
    "snd": true
  },
  {
    "sn": "35165/547373",
    "ab": "parimasudj amen a ljemita qadaw sa tja ljenguaqi a parimasudj a tja kakituluan.",
    "ch": "我們每天都要打掃，大家要把教室打掃乾淨。",
    "en": "We have to clean every day, and everyone has to clean the classroom.",
    "img": "img/33763/525591.jpg",
    "snd": true
  },
  {
    "sn": "35165/547374",
    "ab": "izua vaik a zemuking ta qezung izua vaik a semuap.",
    "ch": "有些人去擦窗戶，有些人去掃地。",
    "en": "Some people clean the windows, some sweep the floor.",
    "img": "img/33763/525592.jpg",
    "snd": true
  },
  {
    "sn": "35165/547375",
    "ab": "parimasudj amen tua putuputung i kgakku na marasurasutj amen a mapuljat a gakku na maparimasutj a ljemita tu qadaw.",
    "ch": "我們還會打掃學校的各個角落，大家分工合作，學校每天都很乾淨。",
    "en": "We will also clean every corner of the school. Everyone works together, and the school is very clean every day.",
    "img": "img/33763/525593.jpg",
    "snd": true
  }
]