[
  {
    "sn": "64345/903955",
    "ab": "se’ulilj aken.",
    "ch": "我跌倒了。",
    "en": "",
    "img": "",
    "snd": true
  },
  {
    "sn": "64345/903956",
    "ab": "mavengav saka maipuq aken.",
    "ch": "我暈倒了。",
    "en": "",
    "img": "",
    "snd": true
  },
  {
    "sn": "64345/903957",
    "ab": "nasekakuda ken.",
    "ch": "我受傷了。",
    "en": "",
    "img": "",
    "snd": true
  },
  {
    "sn": "64345/903958",
    "ab": "pedjamuq a ku cungal.",
    "ch": "我的膝蓋流血了。",
    "en": "",
    "img": "",
    "snd": true
  },
  {
    "sn": "64345/903959",
    "ab": "namapuljaljic anga qaljic na ku cungal.",
    "ch": "我的膝蓋破皮了。",
    "en": "",
    "img": "",
    "snd": true
  },
  {
    "sn": "64345/903960",
    "ab": "na qemacuvung anga ken tua malalumalj.",
    "ch": "我完成了比賽。",
    "en": "",
    "img": "",
    "snd": true
  },
  {
    "sn": "64345/903961",
    "ab": "na ilalumaljan aken tua mekelj.",
    "ch": "我比賽跑步。",
    "en": "",
    "img": "",
    "snd": true
  },
  {
    "sn": "64345/903962",
    "ab": "na ilalumaljan aken tua maqaqesir.",
    "ch": "我比賽拔河。",
    "en": "",
    "img": "",
    "snd": true
  },
  {
    "sn": "64345/903963",
    "ab": "na ilalumaljan aken tua ’emacugan.",
    "ch": "我比賽演講。",
    "en": "",
    "img": "",
    "snd": true
  },
  {
    "sn": "64345/903964",
    "ab": "na ilalumaljan aken tua penanaq.",
    "ch": "我比賽射箭。",
    "en": "",
    "img": "",
    "snd": true
  },
  {
    "sn": "64345/903965",
    "ab": "napaljizav aken tua iyugi.",
    "ch": "我表演跳舞。",
    "en": "",
    "img": "",
    "snd": true
  },
  {
    "sn": "64345/903966",
    "ab": "napaljizav aken tua semenay.",
    "ch": "我表演唱歌。",
    "en": "",
    "img": "",
    "snd": true
  },
  {
    "sn": "64345/903967",
    "ab": "izua malalumalj tua maqaqesir tucu a qadav i gakku.",
    "ch": "學校今天有拔河比賽。",
    "en": "",
    "img": "",
    "snd": true
  },
  {
    "sn": "64345/903968",
    "ab": "izua malalumalj tua djemakadjak ta mali tucu a qadav i gakku.",
    "ch": "學校今天有足球比賽。",
    "en": "",
    "img": "",
    "snd": true
  },
  {
    "sn": "64345/903969",
    "ab": "izua malalumalj tua iyugi tatiav i gakku.",
    "ch": "學校昨天有跳舞比賽。",
    "en": "",
    "img": "",
    "snd": true
  },
  {
    "sn": "64345/903970",
    "ab": "izua malalumalj tua penanaq tatiav i gakku.",
    "ch": "學校明天有射箭比賽。",
    "en": "",
    "img": "",
    "snd": true
  },
  {
    "sn": "64345/903971",
    "ab": "na ilalumaljan aken tua mekelj tucu a qadav.",
    "ch": "我今天有跑步比賽。",
    "en": "",
    "img": "",
    "snd": true
  },
  {
    "sn": "64345/903972",
    "ab": "uri ilalumaljan aken tua cuitjiu nutiav.",
    "ch": "我明天有槌球比賽。",
    "en": "",
    "img": "",
    "snd": true
  },
  {
    "sn": "64345/903973",
    "ab": "na ilalumaljan aken tua semaney tatiav.",
    "ch": "我昨天有唱歌比賽。",
    "en": "",
    "img": "",
    "snd": true
  }
]