{
  "title": "tuki",
  "titleCh": "時鐘",
  "soundPath": null,
  "sentence": [
    {
      "chinese": "時鐘有兩支針，",
      "ab": "tuki ga kyan sazing rom nya,",
      "order": "1",
      "sound": "https://d2y1wf6g5bpaph.cloudfront.net/files/2024/12/12/122c80d9d16a4fc0b4bf82a27ab174c3.mp3",
      "word": [
        {
          "ab": "tuki",
          "ch": "時鐘",
          "sound": "https://d2y1wf6g5bpaph.cloudfront.net/files/2024/12/12/a33fbe19f63775349316700f78d2d7fc.mp3"
        },
        {
          "ab": "ga",
          "ch": "[虛]",
          "sound": "https://d2y1wf6g5bpaph.cloudfront.net/files/2024/12/12/0d7692e7a55eb1d22f4f432cd14c4ef6.mp3"
        },
        {
          "ab": "kyan",
          "ch": "有",
          "sound": "https://d2y1wf6g5bpaph.cloudfront.net/files/2024/12/12/aa7000d98b7b93a0b6bc3623d5cf66e8.mp3"
        },
        {
          "ab": "sazing",
          "ch": "二",
          "sound": "https://d2y1wf6g5bpaph.cloudfront.net/files/2024/12/12/3af4e5761f1bc171394e5d8f3e37aa79.mp3"
        },
        {
          "ab": "rom",
          "ch": "針",
          "sound": "https://d2y1wf6g5bpaph.cloudfront.net/files/2024/12/12/5da3a96599d258488945c0bad70c0dfa.mp3"
        },
        {
          "ab": "nya",
          "ch": "[屬]",
          "sound": "https://d2y1wf6g5bpaph.cloudfront.net/files/2024/12/12/770e73e1fa22e4ee01e2dba10cec6680.mp3"
        },
        {
          "ab": ",",
          "ch": "",
          "sound": null
        }
      ]
    },
    {
      "chinese": "一支長，一支短。",
      "ab": "utux ruyux ru utux r’tung.",
      "order": "2",
      "sound": "https://d2y1wf6g5bpaph.cloudfront.net/files/2024/12/12/f51ace0bc9e520825b5b35d42ceb6090.mp3",
      "word": [
        {
          "ab": "utux",
          "ch": "一",
          "sound": "https://d2y1wf6g5bpaph.cloudfront.net/files/2024/12/12/c1b0591c0d7b7a0e4a2f4a4a783dcdba.mp3"
        },
        {
          "ab": "ruyux",
          "ch": "長",
          "sound": "https://d2y1wf6g5bpaph.cloudfront.net/files/2024/12/12/de0ee62117b14dfceab7dcc4d5b45c8a.mp3"
        },
        {
          "ab": "ru",
          "ch": "及",
          "sound": "https://d2y1wf6g5bpaph.cloudfront.net/files/2024/12/12/276f9986a63277e140f766c7f95c5b9d.mp3"
        },
        {
          "ab": "utux",
          "ch": "一",
          "sound": "https://d2y1wf6g5bpaph.cloudfront.net/files/2024/12/12/5d759cb5421aecee7fa00485beba5fb0.mp3"
        },
        {
          "ab": "r’tung",
          "ch": "短",
          "sound": "https://d2y1wf6g5bpaph.cloudfront.net/files/2024/12/12/1ecf54a69d89f3f4c63fadaf07dcf0a1.mp3"
        },
        {
          "ab": ".",
          "ch": "",
          "sound": null
        }
      ]
    },
    {
      "chinese": "長針轉得快，一天轉二十四圈。",
      "ab": "ruyux rom ga helaw miray, utux ryax ga miray mpusan payat pinrayan.",
      "order": "3",
      "sound": "https://d2y1wf6g5bpaph.cloudfront.net/files/2024/12/12/b4d130ea17306caeea1329ffe8e05ead.mp3",
      "word": [
        {
          "ab": "ruyux rom",
          "ch": "長針",
          "sound": "https://d2y1wf6g5bpaph.cloudfront.net/files/2024/12/12/a2008538adaaf9d909c0e0b5843e8816.mp3"
        },
        {
          "ab": "ga",
          "ch": "[虛]",
          "sound": "https://d2y1wf6g5bpaph.cloudfront.net/files/2024/12/12/d7ab5fc4060d7cd126fe197f22f49701.mp3"
        },
        {
          "ab": "helaw",
          "ch": "快",
          "sound": "https://d2y1wf6g5bpaph.cloudfront.net/files/2024/12/12/5093fd50312c458c6ae67f40ab29f107.mp3"
        },
        {
          "ab": "miray",
          "ch": "轉",
          "sound": "https://d2y1wf6g5bpaph.cloudfront.net/files/2024/12/12/e7b18c68fa2f56b584a5194b52634e16.mp3"
        },
        {
          "ab": ",",
          "ch": "",
          "sound": null
        },
        {
          "ab": "utux",
          "ch": "一",
          "sound": "https://d2y1wf6g5bpaph.cloudfront.net/files/2024/12/12/9602ad4906dfa94943ffbe0bb67e88ff.mp3"
        },
        {
          "ab": "ryax",
          "ch": "天",
          "sound": "https://d2y1wf6g5bpaph.cloudfront.net/files/2024/12/12/5c8c83dfaed10e1115124258aaa90c46.mp3"
        },
        {
          "ab": "ga",
          "ch": "[虛]",
          "sound": "https://d2y1wf6g5bpaph.cloudfront.net/files/2024/12/12/f4c7c84efe8a4546024b1fef613efbb6.mp3"
        },
        {
          "ab": "miray",
          "ch": "轉",
          "sound": "https://d2y1wf6g5bpaph.cloudfront.net/files/2024/12/12/e5507d00f912a1a1772191fb53961197.mp3"
        },
        {
          "ab": "mpusan payat",
          "ch": "二十四",
          "sound": "https://d2y1wf6g5bpaph.cloudfront.net/files/2024/12/12/3145617d7aa69ab05d826190ec39934a.mp3"
        },
        {
          "ab": "pinrayan",
          "ch": "圈",
          "sound": "https://d2y1wf6g5bpaph.cloudfront.net/files/2024/12/12/c9ac6fafaf89b23c863a62750f758926.mp3"
        },
        {
          "ab": ".",
          "ch": "",
          "sound": null
        }
      ]
    },
    {
      "chinese": "短針轉得慢，一天轉兩圈。",
      "ab": "r’tung rom ga thhway miray, utux ryax ga miray sazing pinrayan.",
      "order": "4",
      "sound": "https://d2y1wf6g5bpaph.cloudfront.net/files/2024/12/12/ca061790b7866dfc712d4c12a03c0f5d.mp3",
      "word": [
        {
          "ab": "r’tung rom",
          "ch": "短針",
          "sound": "https://d2y1wf6g5bpaph.cloudfront.net/files/2024/12/12/70002465c5b857de93e9cfeaef7c1adc.mp3"
        },
        {
          "ab": "ga",
          "ch": "[虛]",
          "sound": "https://d2y1wf6g5bpaph.cloudfront.net/files/2024/12/12/ceb0b0dd1a5a9e56813692b11cdf30c3.mp3"
        },
        {
          "ab": "thhway",
          "ch": "慢",
          "sound": "https://d2y1wf6g5bpaph.cloudfront.net/files/2024/12/12/6100bb5d2022de3408429c485847ec51.mp3"
        },
        {
          "ab": "miray",
          "ch": "轉",
          "sound": "https://d2y1wf6g5bpaph.cloudfront.net/files/2024/12/12/1e7dada8162e6695176b38c360a2cfbf.mp3"
        },
        {
          "ab": ",",
          "ch": "",
          "sound": null
        },
        {
          "ab": "utux",
          "ch": "一",
          "sound": "https://d2y1wf6g5bpaph.cloudfront.net/files/2024/12/12/b1be5fe6d628c377e338ff4c0c6918fb.mp3"
        },
        {
          "ab": "ryax",
          "ch": "天",
          "sound": "https://d2y1wf6g5bpaph.cloudfront.net/files/2024/12/12/42c3fcb575076cd65951c87732edb7f6.mp3"
        },
        {
          "ab": "ga",
          "ch": "[虛]",
          "sound": "https://d2y1wf6g5bpaph.cloudfront.net/files/2024/12/12/b2bc2656bbb2e4ba7167a535b11d9baa.mp3"
        },
        {
          "ab": "miray",
          "ch": "轉",
          "sound": "https://d2y1wf6g5bpaph.cloudfront.net/files/2024/12/12/c4bb285c01cbc197ba1244e376f885bf.mp3"
        },
        {
          "ab": "sazing",
          "ch": "二",
          "sound": "https://d2y1wf6g5bpaph.cloudfront.net/files/2024/12/12/cb05be03649ba008ddb3af6563942f7c.mp3"
        },
        {
          "ab": "pinrayan",
          "ch": "圈",
          "sound": "https://d2y1wf6g5bpaph.cloudfront.net/files/2024/12/12/c49629e88f9e9f6f11be100dce1dd951.mp3"
        },
        {
          "ab": ".",
          "ch": "",
          "sound": null
        }
      ]
    },
    {
      "chinese": "從早上到晚上，不停地轉動。",
      "ab": "aring mgyebu tehuk sku gbyan, ini phngi miray.",
      "order": "5",
      "sound": "https://d2y1wf6g5bpaph.cloudfront.net/files/2024/12/12/d2cd09f8898fea9067fdd40674168387.mp3",
      "word": [
        {
          "ab": "aring",
          "ch": "從",
          "sound": "https://d2y1wf6g5bpaph.cloudfront.net/files/2024/12/12/cfd51ac7fbe49645f6ab253bd8cd1816.mp3"
        },
        {
          "ab": "mgyebu",
          "ch": "早上",
          "sound": "https://d2y1wf6g5bpaph.cloudfront.net/files/2024/12/12/3489e21b4a1240d61d45c38e40f376a8.mp3"
        },
        {
          "ab": "tehuk",
          "ch": "到",
          "sound": "https://d2y1wf6g5bpaph.cloudfront.net/files/2024/12/12/40ef3180969b3d5dcd75b04e02b2aa0d.mp3"
        },
        {
          "ab": "sku",
          "ch": "[位]",
          "sound": "https://d2y1wf6g5bpaph.cloudfront.net/files/2024/12/12/e790a9d553007a4478b7191ec0fdeddc.mp3"
        },
        {
          "ab": "gbyan",
          "ch": "晚上",
          "sound": "https://d2y1wf6g5bpaph.cloudfront.net/files/2024/12/12/e2d052ef28495e232ead12f88e2580d7.mp3"
        },
        {
          "ab": ",",
          "ch": "",
          "sound": null
        },
        {
          "ab": "ini",
          "ch": "不",
          "sound": "https://d2y1wf6g5bpaph.cloudfront.net/files/2024/12/12/edf136ea4b8d6ea43f221d3ec0681d1b.mp3"
        },
        {
          "ab": "phngi",
          "ch": "停",
          "sound": "https://d2y1wf6g5bpaph.cloudfront.net/files/2024/12/12/751d199d44fb20bd68dde94c5a1867c0.mp3"
        },
        {
          "ab": "miray",
          "ch": "轉",
          "sound": "https://d2y1wf6g5bpaph.cloudfront.net/files/2024/12/12/2ba6a81c38d194da9f619f24d7504778.mp3"
        },
        {
          "ab": ".",
          "ch": "",
          "sound": null
        }
      ]
    },
    {
      "chinese": "好像在告訴我們，要愛惜時間。",
      "ab": "giwan/siga niya psba ita maha, laxiy hiri ryax.",
      "order": "6",
      "sound": "https://d2y1wf6g5bpaph.cloudfront.net/files/2024/12/12/f667c6942814043dcb80e2db734811e5.mp3",
      "word": [
        {
          "ab": "giwan/siga",
          "ch": "等於；好像",
          "sound": "https://d2y1wf6g5bpaph.cloudfront.net/files/2024/12/12/2778a684f152d1821cd1aa6f752b54fe.mp3"
        },
        {
          "ab": "niya",
          "ch": "在",
          "sound": "https://d2y1wf6g5bpaph.cloudfront.net/files/2024/12/12/5e63991730ed9c0ae6ea6a970d2a53aa.mp3"
        },
        {
          "ab": "psba",
          "ch": "教導",
          "sound": "https://d2y1wf6g5bpaph.cloudfront.net/files/2024/12/12/b65d8ec431482fd116cb0d8435262e94.mp3"
        },
        {
          "ab": "ita",
          "ch": "我們",
          "sound": "https://d2y1wf6g5bpaph.cloudfront.net/files/2024/12/12/81ef57ee0d8fb3ecfe59179d0e88a5fc.mp3"
        },
        {
          "ab": "maha",
          "ch": "說",
          "sound": "https://d2y1wf6g5bpaph.cloudfront.net/files/2024/12/12/6ffba9136ff7fef6be7fe15e30311ea8.mp3"
        },
        {
          "ab": ",",
          "ch": "",
          "sound": null
        },
        {
          "ab": "laxiy",
          "ch": "不要",
          "sound": "https://d2y1wf6g5bpaph.cloudfront.net/files/2024/12/12/27f1c23506167836c2afe9fdbd458060.mp3"
        },
        {
          "ab": "hiri",
          "ch": "浪費",
          "sound": "https://d2y1wf6g5bpaph.cloudfront.net/files/2024/12/12/f08a95354ec65bd08f4cc30a02759d4c.mp3"
        },
        {
          "ab": "ryax",
          "ch": "時間",
          "sound": "https://d2y1wf6g5bpaph.cloudfront.net/files/2024/12/12/36c69d1283a71ce635b3cdf3a4763853.mp3"
        },
        {
          "ab": ".",
          "ch": "",
          "sound": null
        }
      ]
    }
  ]
}