{
  "title": "U tamedaw nu luma’ nu niyam",
  "titleCh": "我們一家人",
  "soundPath": null,
  "sentence": [
    {
      "chinese": "我們家有五個人。",
      "ab": "Lalima ku tamedaw nu luma’ nu niyam.",
      "order": "1",
      "sound": "https://d2y1wf6g5bpaph.cloudfront.net/sound/2018/02/13/bdad073d2c77b0525e32a0e9784089ea.wav",
      "word": [
        {
          "ab": "Lalima",
          "ch": "五",
          "sound": "https://d2y1wf6g5bpaph.cloudfront.net/sound/2018/02/13/f02a8fde79ddf5b978cd9ae9d408b7c1.wav"
        },
        {
          "ab": "ku",
          "ch": "[虛]",
          "sound": "https://d2y1wf6g5bpaph.cloudfront.net/sound/2018/02/13/7012ef0335aa2adbab58bd6d0702ba41.wav"
        },
        {
          "ab": "tamedaw",
          "ch": "人",
          "sound": "https://d2y1wf6g5bpaph.cloudfront.net/sound/2018/02/13/dac32839a9f0baae954b41abee610cc0.wav"
        },
        {
          "ab": "nu",
          "ch": "[虛]",
          "sound": "https://d2y1wf6g5bpaph.cloudfront.net/sound/2018/02/13/488b084119a1c7a4950f00706ec7ea16.wav"
        },
        {
          "ab": "luma’",
          "ch": "家",
          "sound": "https://d2y1wf6g5bpaph.cloudfront.net/sound/2018/02/13/1cb524b5a3f3f82be4a7d954063c07e2.wav"
        },
        {
          "ab": "nu",
          "ch": "[虛]",
          "sound": "https://d2y1wf6g5bpaph.cloudfront.net/sound/2018/02/13/df438e5206f31600e6ae4af72f2725f1.wav"
        },
        {
          "ab": "niyam",
          "ch": "我們（的）",
          "sound": "https://d2y1wf6g5bpaph.cloudfront.net/sound/2018/02/13/3bf29f38421bc1764e6f1d1545479f93.wav"
        },
        {
          "ab": ".",
          "ch": "",
          "sound": null
        }
      ]
    },
    {
      "chinese": "祖母、爸爸、媽媽、妹妹和我。",
      "ab": "U vayi, u wama, u wina, u vavahiyan a sava atu kaku.",
      "order": "2",
      "sound": "https://d2y1wf6g5bpaph.cloudfront.net/sound/2018/02/13/413894b7e2c6dfc6e8a0e9f18287e3c4.wav",
      "word": [
        {
          "ab": "U",
          "ch": "[虛]",
          "sound": "https://d2y1wf6g5bpaph.cloudfront.net/sound/2018/02/13/1e9f65024cd764a33b94a14b0e79f42d.wav"
        },
        {
          "ab": "vayi",
          "ch": "祖母",
          "sound": "https://d2y1wf6g5bpaph.cloudfront.net/sound/2018/02/13/0dbd53751c00e0784799008b44471a77.wav"
        },
        {
          "ab": ",",
          "ch": "",
          "sound": null
        },
        {
          "ab": "u",
          "ch": "[虛]",
          "sound": "https://d2y1wf6g5bpaph.cloudfront.net/sound/2018/02/13/f8e6ba1db0f3c4054afec1684ba8fb26.wav"
        },
        {
          "ab": "wama",
          "ch": "爸爸",
          "sound": "https://d2y1wf6g5bpaph.cloudfront.net/sound/2018/02/13/5c2631d54272554b181cf21ad2171fa3.wav"
        },
        {
          "ab": ",",
          "ch": "",
          "sound": null
        },
        {
          "ab": "u",
          "ch": "[虛]",
          "sound": "https://d2y1wf6g5bpaph.cloudfront.net/sound/2018/02/13/504b7f668328dab60570f03ecfe47918.wav"
        },
        {
          "ab": "wina",
          "ch": "媽媽\r\nu ina = wina",
          "sound": "https://d2y1wf6g5bpaph.cloudfront.net/sound/2018/02/13/ff096d0e005a8c794b6c1da7c0fd662e.wav"
        },
        {
          "ab": ",",
          "ch": "",
          "sound": null
        },
        {
          "ab": "u",
          "ch": "[虛]",
          "sound": "https://d2y1wf6g5bpaph.cloudfront.net/sound/2018/02/13/7cc980b0f894bd0cf05c37c246f215f3.wav"
        },
        {
          "ab": "vavahiyan a sava",
          "ch": "妹妹",
          "sound": "https://d2y1wf6g5bpaph.cloudfront.net/sound/2018/02/13/328347805873e9a9c700591812fb0ec2.wav"
        },
        {
          "ab": "atu",
          "ch": "和",
          "sound": "https://d2y1wf6g5bpaph.cloudfront.net/sound/2018/02/13/d4a93297083a23cc099f7bd6a8621131.wav"
        },
        {
          "ab": "kaku",
          "ch": "我",
          "sound": "https://d2y1wf6g5bpaph.cloudfront.net/sound/2018/02/13/9ae0a504e3af13e2e6b3ff478a8f637b.wav"
        },
        {
          "ab": ".",
          "ch": "",
          "sound": null
        }
      ]
    },
    {
      "chinese": "我在學校讀書。",
      "ab": "Micudad kaku i cacudadan.",
      "order": "3",
      "sound": "https://d2y1wf6g5bpaph.cloudfront.net/sound/2018/02/13/96bda159871048d8a36f197dfce668a4.wav",
      "word": [
        {
          "ab": "Micudad",
          "ch": "讀書",
          "sound": "https://d2y1wf6g5bpaph.cloudfront.net/sound/2018/02/13/7e185cc0ad0a719c730af5354d7142c1.wav"
        },
        {
          "ab": "kaku",
          "ch": "我",
          "sound": "https://d2y1wf6g5bpaph.cloudfront.net/sound/2018/02/13/ea3aed2bce2d893088e71e188ebca823.wav"
        },
        {
          "ab": "i",
          "ch": "[虛]",
          "sound": "https://d2y1wf6g5bpaph.cloudfront.net/sound/2018/02/13/993edc98ca87f7e08494eec37fa836f7.wav"
        },
        {
          "ab": "cacudadan",
          "ch": "學校",
          "sound": "https://d2y1wf6g5bpaph.cloudfront.net/sound/2018/02/13/b33128cb0089003ddfb5199e1b679652.wav"
        },
        {
          "ab": ".",
          "ch": "",
          "sound": null
        }
      ]
    },
    {
      "chinese": "我的妹妹在幼稚園讀書。",
      "ab": "Micudad ku vavahiyan a sava nu maku i yuciing.",
      "order": "4",
      "sound": "https://d2y1wf6g5bpaph.cloudfront.net/sound/2018/02/13/c9d9edbf9b9e23eb5d4819bbcce9b078.wav",
      "word": [
        {
          "ab": "Micudad",
          "ch": "讀書",
          "sound": "https://d2y1wf6g5bpaph.cloudfront.net/sound/2018/02/13/62b98e188905060143a433b1363b3266.wav"
        },
        {
          "ab": "ku",
          "ch": "[虛]",
          "sound": "https://d2y1wf6g5bpaph.cloudfront.net/sound/2018/02/13/2be8328f41144106f7144802f2367487.wav"
        },
        {
          "ab": "vavahiyan a sava nu maku",
          "ch": "我的妹妹",
          "sound": "https://d2y1wf6g5bpaph.cloudfront.net/sound/2018/02/13/4cc05b35c2f937c5bd9e7d41d3686fff.wav"
        },
        {
          "ab": "i",
          "ch": "[虛]",
          "sound": "https://d2y1wf6g5bpaph.cloudfront.net/sound/2018/02/13/a9d34fb66d81367590fdd5337324233a.wav"
        },
        {
          "ab": "yuciing",
          "ch": "幼稚園",
          "sound": "https://d2y1wf6g5bpaph.cloudfront.net/sound/2018/02/13/09676fac73eda6cac726c43e43e86c58.wav"
        },
        {
          "ab": ".",
          "ch": "",
          "sound": null
        }
      ]
    }
  ]
}