{
  "title": "Mafana’ kako a caciyaw to no ’Amis",
  "titleCh": "我會講阿美族話",
  "soundPath": null,
  "sentence": [
    {
      "chinese": "你會講阿美族話嗎？",
      "ab": "Mafana’ay a caciyaw to sowal no ’Amis kiso haw?",
      "order": "1",
      "sound": "https://d2y1wf6g5bpaph.cloudfront.net/sound/2019/07/25/3a0622c79183393cccb641816b11ceb8.wav",
      "word": [
        {
          "ab": "Mafana’ay",
          "ch": "會的",
          "sound": "https://d2y1wf6g5bpaph.cloudfront.net/sound/2019/07/25/d3bef63db6331fc71b0fc42947641d07.wav"
        },
        {
          "ab": "a",
          "ch": "[連]",
          "sound": "https://d2y1wf6g5bpaph.cloudfront.net/sound/2019/07/25/67d5a9afe50591f627fee6e2d0b5f3d9.wav"
        },
        {
          "ab": "caciyaw",
          "ch": "講",
          "sound": "https://d2y1wf6g5bpaph.cloudfront.net/sound/2019/07/25/423b7ef9d4607f3a3b687e5ae6610343.wav"
        },
        {
          "ab": "to",
          "ch": "[受]",
          "sound": "https://d2y1wf6g5bpaph.cloudfront.net/sound/2019/07/25/71d86b440e013f1effe5db48103bf390.wav"
        },
        {
          "ab": "sowal",
          "ch": "話",
          "sound": "https://d2y1wf6g5bpaph.cloudfront.net/sound/2019/07/25/e46f46aaae12dd2a8503d14aeb8e0b29.wav"
        },
        {
          "ab": "no",
          "ch": "[屬]",
          "sound": "https://d2y1wf6g5bpaph.cloudfront.net/sound/2019/07/25/3c6958f950d3a5e880af1620b5f8f0e4.wav"
        },
        {
          "ab": "’Amis",
          "ch": "阿美族",
          "sound": "https://d2y1wf6g5bpaph.cloudfront.net/sound/2019/07/25/fdd67045817a615e7dd3ca19395de28a.wav"
        },
        {
          "ab": "kiso",
          "ch": "你",
          "sound": "https://d2y1wf6g5bpaph.cloudfront.net/sound/2019/07/25/a32becd25e5fddf6f46e4739f5ee47d5.wav"
        },
        {
          "ab": "haw",
          "ch": "嗎",
          "sound": "https://d2y1wf6g5bpaph.cloudfront.net/sound/2019/07/25/d7c543db73dea814ad975cbc3d93de66.wav"
        },
        {
          "ab": "?",
          "ch": "",
          "sound": null
        }
      ]
    },
    {
      "chinese": "會一點點，我正在學習。",
      "ab": "Mimingay ko kafana’an, mihatatanamay ho kako.",
      "order": "2",
      "sound": "https://d2y1wf6g5bpaph.cloudfront.net/sound/2019/07/19/6c210e79c32a706a3135b38d24d4701a.wav",
      "word": [
        {
          "ab": "Mimingay",
          "ch": "一點點",
          "sound": "https://d2y1wf6g5bpaph.cloudfront.net/sound/2019/07/25/f71c97ae35da32090c07e9876b929376.wav"
        },
        {
          "ab": "ko",
          "ch": "[主]",
          "sound": "https://d2y1wf6g5bpaph.cloudfront.net/sound/2019/07/25/695d31c162e6a9af1c8951a0ed319290.wav"
        },
        {
          "ab": "kafana’an",
          "ch": "會的",
          "sound": "https://d2y1wf6g5bpaph.cloudfront.net/sound/2019/07/25/67d6cdc051dfc447469a6a5b897c7319.wav"
        },
        {
          "ab": ",",
          "ch": "",
          "sound": null
        },
        {
          "ab": "mihatatanamay",
          "ch": "在學習中",
          "sound": "https://d2y1wf6g5bpaph.cloudfront.net/sound/2019/07/25/2e3a76f3a3e82b2e39d1f442d6a5766d.wav"
        },
        {
          "ab": "ho",
          "ch": "還",
          "sound": "https://d2y1wf6g5bpaph.cloudfront.net/sound/2019/07/25/c5ad8799a22da20087185c2db36ad087.wav"
        },
        {
          "ab": "kako",
          "ch": "我",
          "sound": "https://d2y1wf6g5bpaph.cloudfront.net/sound/2019/07/25/fb7803b27c9b16d2bd8da9e48c035514.wav"
        },
        {
          "ab": ".",
          "ch": "",
          "sound": null
        }
      ]
    },
    {
      "chinese": "你在哪裡學習阿美族話？",
      "ab": "I cowaay a mihatatanam to sowal no ’Amis kiso?",
      "order": "3",
      "sound": "https://d2y1wf6g5bpaph.cloudfront.net/sound/2019/07/29/a6e9cc012d84e6a9f6facf941bae2c1b.wav",
      "word": [
        {
          "ab": "I",
          "ch": "[介]",
          "sound": "https://d2y1wf6g5bpaph.cloudfront.net/sound/2019/07/25/42f71abe3045bf67793f5773f28c87e5.wav"
        },
        {
          "ab": "cowaay",
          "ch": "哪裡",
          "sound": "https://d2y1wf6g5bpaph.cloudfront.net/sound/2019/07/25/75ed56031c85e288ef65f6783433713a.wav"
        },
        {
          "ab": "a",
          "ch": "[連]",
          "sound": "https://d2y1wf6g5bpaph.cloudfront.net/sound/2019/07/25/13ac17aa38effdd56772b72f57e2ab3c.wav"
        },
        {
          "ab": "mihatatanam",
          "ch": "學習",
          "sound": "https://d2y1wf6g5bpaph.cloudfront.net/sound/2019/07/25/c4e73e5c40be1c5c724a768986077a9d.wav"
        },
        {
          "ab": "to",
          "ch": "[受]",
          "sound": "https://d2y1wf6g5bpaph.cloudfront.net/sound/2019/07/25/d21df5643f52f897712189f259e0d7a5.wav"
        },
        {
          "ab": "sowal",
          "ch": "語言",
          "sound": "https://d2y1wf6g5bpaph.cloudfront.net/sound/2019/07/25/f1e104092723330294141b6e555359a5.wav"
        },
        {
          "ab": "no",
          "ch": "[屬]",
          "sound": "https://d2y1wf6g5bpaph.cloudfront.net/sound/2019/07/25/4784375dfb4841c1ad72f10dc3aef27d.wav"
        },
        {
          "ab": "’Amis",
          "ch": "阿美族",
          "sound": "https://d2y1wf6g5bpaph.cloudfront.net/sound/2019/07/25/27dafd7f51714768baba53df14481af9.wav"
        },
        {
          "ab": "kiso",
          "ch": "你",
          "sound": "https://d2y1wf6g5bpaph.cloudfront.net/sound/2019/07/25/46112a1cbef5f3fbf297557abfae70fe.wav"
        },
        {
          "ab": "?",
          "ch": "",
          "sound": null
        }
      ]
    },
    {
      "chinese": "我在學校學習。",
      "ab": "I kongkoan mihatatanam kako.",
      "order": "4",
      "sound": "https://d2y1wf6g5bpaph.cloudfront.net/sound/2019/07/19/ec5e020bed449f3436303fd0d0b58b53.wav",
      "word": [
        {
          "ab": "I",
          "ch": "[介]",
          "sound": "https://d2y1wf6g5bpaph.cloudfront.net/sound/2019/07/25/ecc4f9d9bd6c3b3735bc251d2713b0c6.wav"
        },
        {
          "ab": "kongkoan",
          "ch": "學校",
          "sound": "https://d2y1wf6g5bpaph.cloudfront.net/sound/2019/07/25/63e67571c3df64c05116ba91491454e7.wav"
        },
        {
          "ab": "mihatatanam",
          "ch": "學習",
          "sound": "https://d2y1wf6g5bpaph.cloudfront.net/sound/2019/07/25/61719f64dc721bc158f235cabc323efd.wav"
        },
        {
          "ab": "kako",
          "ch": "我",
          "sound": "https://d2y1wf6g5bpaph.cloudfront.net/sound/2019/07/25/8d6a741e720b6eb8a548bc74723ff365.wav"
        },
        {
          "ab": ".",
          "ch": "",
          "sound": null
        }
      ]
    },
    {
      "chinese": "阿美族話好學嗎？",
      "ab": "Lahoday a nanamen ko sowal no ’Amis haw?",
      "order": "5",
      "sound": "https://d2y1wf6g5bpaph.cloudfront.net/sound/2019/07/25/cddac242d5f79a1d4025756a53e43f56.wav",
      "word": [
        {
          "ab": "Lahoday",
          "ch": "容易",
          "sound": "https://d2y1wf6g5bpaph.cloudfront.net/sound/2019/07/25/1041d2ca24a0cc08f0b2d094bb36e00a.wav"
        },
        {
          "ab": "a",
          "ch": "[連]",
          "sound": "https://d2y1wf6g5bpaph.cloudfront.net/sound/2019/07/25/0a009cd711b8df9ea6f57bfd737dd495.wav"
        },
        {
          "ab": "nanamen",
          "ch": "學習",
          "sound": "https://d2y1wf6g5bpaph.cloudfront.net/sound/2019/07/30/731f642bf46bb4466883bc3ed441f341.wav"
        },
        {
          "ab": "ko",
          "ch": "[主]",
          "sound": "https://d2y1wf6g5bpaph.cloudfront.net/sound/2019/07/25/fa2c06488daaa319201d2bc5c0de8982.wav"
        },
        {
          "ab": "sowal",
          "ch": "語言",
          "sound": "https://d2y1wf6g5bpaph.cloudfront.net/sound/2019/07/25/54cf8860b63fc1abd7e2a9c6f71fa27b.wav"
        },
        {
          "ab": "no",
          "ch": "[屬]",
          "sound": "https://d2y1wf6g5bpaph.cloudfront.net/sound/2019/07/25/80e132a4dee260b300b5b3dc1523caf5.wav"
        },
        {
          "ab": "’Amis",
          "ch": "阿美族",
          "sound": "https://d2y1wf6g5bpaph.cloudfront.net/sound/2019/07/25/459a0c7f33b153132c30b45885d90238.wav"
        },
        {
          "ab": "haw",
          "ch": "嗎",
          "sound": "https://d2y1wf6g5bpaph.cloudfront.net/sound/2019/07/25/090740b4784e4f940a6d30f625509ab8.wav"
        },
        {
          "ab": "?",
          "ch": "",
          "sound": null
        }
      ]
    },
    {
      "chinese": "很好學！非常有趣。",
      "ab": "Lahoday a nanamen! Tadakahemekan to.",
      "order": "6",
      "sound": "https://d2y1wf6g5bpaph.cloudfront.net/sound/2019/07/19/a771e8fc302db2c522c6bb19ad881cf4.wav",
      "word": [
        {
          "ab": "Lahoday",
          "ch": "容易",
          "sound": "https://d2y1wf6g5bpaph.cloudfront.net/sound/2019/07/25/1407187f64406758a7d767c576a3f977.wav"
        },
        {
          "ab": "a",
          "ch": "[連]",
          "sound": "https://d2y1wf6g5bpaph.cloudfront.net/sound/2019/07/25/3b94b41d9a3005bf8728706d22ab7a99.wav"
        },
        {
          "ab": "nanamen",
          "ch": "學習",
          "sound": "https://d2y1wf6g5bpaph.cloudfront.net/sound/2019/07/25/6fe6e5eb96e3a4a723377d24c281ac30.wav"
        },
        {
          "ab": "!",
          "ch": "",
          "sound": null
        },
        {
          "ab": "Tadakahemekan",
          "ch": "非常有趣的",
          "sound": "https://d2y1wf6g5bpaph.cloudfront.net/sound/2019/07/25/b3b9d0603cf68ec9edd6bf0ca51f56f4.wav"
        },
        {
          "ab": "to",
          "ch": "了",
          "sound": "https://d2y1wf6g5bpaph.cloudfront.net/sound/2019/07/25/95961d2857d99ff8935f79feacf45652.wav"
        },
        {
          "ab": ".",
          "ch": "",
          "sound": null
        }
      ]
    },
    {
      "chinese": "你很會講阿美族話。",
      "ab": "Mafana’ay to kiso caciyaw to sowal no ’Amis.",
      "order": "7",
      "sound": "https://d2y1wf6g5bpaph.cloudfront.net/sound/2019/07/25/a9a0340ea906ec9cccae9aea9e5952c1.wav",
      "word": [
        {
          "ab": "Mafana’ay",
          "ch": "很會",
          "sound": "https://d2y1wf6g5bpaph.cloudfront.net/sound/2019/07/25/c95177bfab745c69de72c53889b7c812.wav"
        },
        {
          "ab": "to",
          "ch": "了",
          "sound": "https://d2y1wf6g5bpaph.cloudfront.net/sound/2019/07/25/fc60a30b043ea5e81975a91336898ed8.wav"
        },
        {
          "ab": "kiso",
          "ch": "你",
          "sound": "https://d2y1wf6g5bpaph.cloudfront.net/sound/2019/07/25/c94cef2abce46dbb519766603fa2d943.wav"
        },
        {
          "ab": "caciyaw",
          "ch": "講",
          "sound": "https://d2y1wf6g5bpaph.cloudfront.net/sound/2019/07/25/67af42d7a28a26a16719a9114e8b2565.wav"
        },
        {
          "ab": "to",
          "ch": "[受]",
          "sound": "https://d2y1wf6g5bpaph.cloudfront.net/sound/2019/07/25/a2424704f20de7ae8f338a98f4dd9928.wav"
        },
        {
          "ab": "sowal",
          "ch": "語言",
          "sound": "https://d2y1wf6g5bpaph.cloudfront.net/sound/2019/07/25/f70163cbd0676f98566cf24646b36df5.wav"
        },
        {
          "ab": "no",
          "ch": "[屬]",
          "sound": "https://d2y1wf6g5bpaph.cloudfront.net/sound/2019/07/25/a3e15377630a0dabcb5398393a3e5e8c.wav"
        },
        {
          "ab": "’Amis",
          "ch": "阿美族",
          "sound": "https://d2y1wf6g5bpaph.cloudfront.net/sound/2019/07/25/a9860b5d6a7df05bf85fda2242a6bdf1.wav"
        },
        {
          "ab": ".",
          "ch": "",
          "sound": null
        }
      ]
    }
  ]
}