{
  "title": "snatu mu biru na ksuyan mlikuy",
  "titleCh": "我寄給哥哥的信",
  "soundPath": null,
  "sentence": [
    {
      "chinese": "哥哥，你好！",
      "ab": "ksuyan, cyu su lokah ga!",
      "order": "1",
      "sound": "https://d2y1wf6g5bpaph.cloudfront.net/files/2025/01/01/9b786808036edaab8bd6b6ee2fb71cd0.wav",
      "word": [
        {
          "ab": "ksuyan",
          "ch": "哥哥",
          "sound": "https://d2y1wf6g5bpaph.cloudfront.net/files/2025/01/01/84c43991426c7538f679be869062f3c7.wav"
        },
        {
          "ab": ",",
          "ch": "",
          "sound": null
        },
        {
          "ab": "cyu",
          "ch": "有",
          "sound": "https://d2y1wf6g5bpaph.cloudfront.net/files/2025/01/02/af7be84c9eef8a536b5a3ec9ab282bf4.wav"
        },
        {
          "ab": "su",
          "ch": "你",
          "sound": "https://d2y1wf6g5bpaph.cloudfront.net/files/2025/01/02/f102faf57facab3db71d53b42a0bed79.wav"
        },
        {
          "ab": "lokah",
          "ch": "健壯；安好",
          "sound": "https://d2y1wf6g5bpaph.cloudfront.net/files/2025/01/02/a66ace8b750c0ce3cb6674330217ce26.wav"
        },
        {
          "ab": "ga",
          "ch": "嗎",
          "sound": "https://d2y1wf6g5bpaph.cloudfront.net/files/2025/01/02/955a9e1d9ff4af9ec6ae2f0a11d70165.wav"
        },
        {
          "ab": "!",
          "ch": "",
          "sound": null
        }
      ]
    },
    {
      "chinese": "今天接到你的信，我非常高興。",
      "ab": "wa mu galun snatu su biru soni, m’es caku calay.",
      "order": "2",
      "sound": "https://d2y1wf6g5bpaph.cloudfront.net/files/2025/01/02/dfdd3040be8cb0a0a4ea59835e07423a.wav",
      "word": [
        {
          "ab": "wa",
          "ch": "已經",
          "sound": "https://d2y1wf6g5bpaph.cloudfront.net/files/2025/01/02/45c31699c7d6af27a0379fa8f9824b9d.wav"
        },
        {
          "ab": "mu",
          "ch": "我",
          "sound": "https://d2y1wf6g5bpaph.cloudfront.net/files/2025/01/02/b1deb3f056299bd282598d9eb1e927c4.wav"
        },
        {
          "ab": "galun",
          "ch": "接收",
          "sound": "https://d2y1wf6g5bpaph.cloudfront.net/files/2025/01/02/6f61ce47c4bff268417c6a640f663471.wav"
        },
        {
          "ab": "snatu",
          "ch": "所寄的",
          "sound": "https://d2y1wf6g5bpaph.cloudfront.net/files/2025/01/02/480d28c7802dbf5e751477286922da27.wav"
        },
        {
          "ab": "su",
          "ch": "你",
          "sound": "https://d2y1wf6g5bpaph.cloudfront.net/files/2025/01/02/b63c29b4afceb54efef16f3eb01fc1fe.wav"
        },
        {
          "ab": "biru",
          "ch": "信；寫下的話",
          "sound": "https://d2y1wf6g5bpaph.cloudfront.net/files/2025/01/02/bac0fcbfff429f60477fefe0cd7d4f6e.wav"
        },
        {
          "ab": "soni",
          "ch": "今天",
          "sound": "https://d2y1wf6g5bpaph.cloudfront.net/files/2025/01/02/81ec6719593ad070f6c8a597feb6072d.wav"
        },
        {
          "ab": ",",
          "ch": "",
          "sound": null
        },
        {
          "ab": "m’es",
          "ch": "高興",
          "sound": "https://d2y1wf6g5bpaph.cloudfront.net/files/2025/01/02/56d73ba69f329628d8dbc1e9fffc1852.wav"
        },
        {
          "ab": "caku",
          "ch": "我",
          "sound": "https://d2y1wf6g5bpaph.cloudfront.net/files/2025/01/02/3519bc0354ae4962b9a53c1cb05bbc93.wav"
        },
        {
          "ab": "calay",
          "ch": "非常",
          "sound": "https://d2y1wf6g5bpaph.cloudfront.net/files/2025/01/02/ca7b67776da93cc57084c0e5da675e1f.wav"
        },
        {
          "ab": ".",
          "ch": "",
          "sound": null
        }
      ]
    },
    {
      "chinese": "上個月你送給我的三本書，我都很喜歡。",
      "ab": "utux byacing wayan pn’aras su tugan biru ga, sli mu ci kwara.",
      "order": "3",
      "sound": "https://d2y1wf6g5bpaph.cloudfront.net/sound/2021/03/23/12e1753f3ea0968b85147c4f3870fbb5.wav",
      "word": [
        {
          "ab": "utux ",
          "ch": "一個",
          "sound": "https://d2y1wf6g5bpaph.cloudfront.net/files/2025/01/02/af7e61816b66e3017e0c02ee0095c038.wav"
        },
        {
          "ab": "byacing",
          "ch": "月",
          "sound": "https://d2y1wf6g5bpaph.cloudfront.net/files/2025/01/02/56c3a61087221bb6d3f71d15741dc9d5.wav"
        },
        {
          "ab": "wayan",
          "ch": "過去",
          "sound": "https://d2y1wf6g5bpaph.cloudfront.net/sound/2021/03/23/183b6fb5bfdbb8bac40cdceaf65e6c78.wav"
        },
        {
          "ab": "pn’aras",
          "ch": "所寄來的",
          "sound": "https://d2y1wf6g5bpaph.cloudfront.net/files/2025/01/02/5f0264ba09cd317a148938c44a4eff1c.wav"
        },
        {
          "ab": "su",
          "ch": "你",
          "sound": "https://d2y1wf6g5bpaph.cloudfront.net/files/2025/01/02/f086b3e2c885d44954d48dbce3c4e3e3.wav"
        },
        {
          "ab": "tugan",
          "ch": "三",
          "sound": "https://d2y1wf6g5bpaph.cloudfront.net/files/2025/01/02/c3246c2c61c4ac97c8f9c7f31af5313b.wav"
        },
        {
          "ab": "biru",
          "ch": "書籍",
          "sound": "https://d2y1wf6g5bpaph.cloudfront.net/files/2025/01/02/b622cadad3e5e53615e22e3fc068dc35.wav"
        },
        {
          "ab": "ga",
          "ch": "呢",
          "sound": "https://d2y1wf6g5bpaph.cloudfront.net/files/2025/01/02/6a23a22999d9f3e6d809c344a1139b5d.wav"
        },
        {
          "ab": ",",
          "ch": "",
          "sound": null
        },
        {
          "ab": "sli",
          "ch": "喜歡",
          "sound": "https://d2y1wf6g5bpaph.cloudfront.net/sound/2021/03/23/b16c2e60fab536ef5d348ecf2010735c.wav"
        },
        {
          "ab": "mu",
          "ch": "我",
          "sound": "https://d2y1wf6g5bpaph.cloudfront.net/files/2025/01/02/7970495c1519971a9f74d01e90a09fbc.wav"
        },
        {
          "ab": "ci",
          "ch": "很，非常",
          "sound": "https://d2y1wf6g5bpaph.cloudfront.net/files/2025/01/02/200126b9463fdcff733fafd13b7500cc.wav"
        },
        {
          "ab": "kwara",
          "ch": "全部，都",
          "sound": "https://d2y1wf6g5bpaph.cloudfront.net/files/2025/01/02/27d9fbc7849d1f4ea0f253e62bab6d93.wav"
        },
        {
          "ab": ".",
          "ch": "",
          "sound": null
        }
      ]
    },
    {
      "chinese": "聽說你畢業了，就要成為老師。",
      "ab": "pnungan mu waya su masu m’was biru la, mosa su galan psba biru.",
      "order": "4",
      "sound": "https://d2y1wf6g5bpaph.cloudfront.net/files/2025/01/02/2c1af47750c3cb41ac573d52e88e39ef.wav",
      "word": [
        {
          "ab": "pnungan",
          "ch": "曾聽說",
          "sound": "https://d2y1wf6g5bpaph.cloudfront.net/files/2025/01/02/35d966d3c1478d92d1ef0f8637a015f9.wav"
        },
        {
          "ab": "mu",
          "ch": "我",
          "sound": "https://d2y1wf6g5bpaph.cloudfront.net/files/2025/01/02/c5a449308444aa70b8dbcf71effe8e44.wav"
        },
        {
          "ab": "waya",
          "ch": "已經",
          "sound": "https://d2y1wf6g5bpaph.cloudfront.net/files/2025/01/02/94aa19340f1637ba74ca4dfadb5223a6.wav"
        },
        {
          "ab": "su",
          "ch": "你",
          "sound": "https://d2y1wf6g5bpaph.cloudfront.net/files/2025/01/02/8b0a212e35adadb702cd8c9d6b6c40d1.wav"
        },
        {
          "ab": "masu",
          "ch": "結束",
          "sound": "https://d2y1wf6g5bpaph.cloudfront.net/files/2025/01/02/99de76d9c25dea22f21ae8b60173ce5c.wav"
        },
        {
          "ab": "m’was biru",
          "ch": "讀書",
          "sound": "https://d2y1wf6g5bpaph.cloudfront.net/files/2025/01/02/1a116f8a2318c82f166ae6e6fd37158b.wav"
        },
        {
          "ab": "la",
          "ch": "了",
          "sound": "https://d2y1wf6g5bpaph.cloudfront.net/files/2025/01/02/12ae8999911e3949f177ca759a635366.wav"
        },
        {
          "ab": ",",
          "ch": "",
          "sound": null
        },
        {
          "ab": "mosa",
          "ch": "要；成為",
          "sound": "https://d2y1wf6g5bpaph.cloudfront.net/files/2025/01/02/61ad0b7e61094660b576ba7dba781fbf.wav"
        },
        {
          "ab": "su",
          "ch": "你",
          "sound": "https://d2y1wf6g5bpaph.cloudfront.net/files/2025/01/02/6913f923a11c10cfe14ef8695851a731.wav"
        },
        {
          "ab": "galan",
          "ch": "被獲得；被視為",
          "sound": "https://d2y1wf6g5bpaph.cloudfront.net/files/2025/01/02/40664c08a47a6e7013d630c1333caa08.wav"
        },
        {
          "ab": "psba biru",
          "ch": "老師",
          "sound": "https://d2y1wf6g5bpaph.cloudfront.net/files/2025/01/02/859e63ddba22ec7ff65943ab19eb8af8.wav"
        },
        {
          "ab": ".",
          "ch": "",
          "sound": null
        }
      ]
    },
    {
      "chinese": "我也要努力讀書，",
      "ab": "kngiyat caku m’was biru uyi,",
      "order": "5",
      "sound": "https://d2y1wf6g5bpaph.cloudfront.net/files/2025/01/02/4923660c53ba62c684ced956638a45fd.wav",
      "word": [
        {
          "ab": "kngiyat",
          "ch": "努力，勤奮",
          "sound": "https://d2y1wf6g5bpaph.cloudfront.net/files/2025/01/02/2a3e6098cb9608ba0fbb19371ca7fef0.wav"
        },
        {
          "ab": "caku",
          "ch": "我",
          "sound": "https://d2y1wf6g5bpaph.cloudfront.net/files/2025/01/02/56de19582c251f7a07d82c8de2c2d131.wav"
        },
        {
          "ab": "m’was biru",
          "ch": "讀書",
          "sound": "https://d2y1wf6g5bpaph.cloudfront.net/sound/2020/05/06/65891e69e3ad789d3867689e0d15cac5.wav"
        },
        {
          "ab": "uyi",
          "ch": "也要",
          "sound": "https://d2y1wf6g5bpaph.cloudfront.net/sound/2020/05/06/44e17c0c11614e2c962d72139a55185f.wav"
        },
        {
          "ab": ",",
          "ch": "",
          "sound": null
        }
      ]
    },
    {
      "chinese": "希望和你一樣，將來做個優秀的老師。",
      "ab": "aki cu yani isu, babaw nya ga mosa cu galan myasa ci psba biru.",
      "order": "6",
      "sound": "https://d2y1wf6g5bpaph.cloudfront.net/files/2025/01/02/9a49cdf525551373364ae21ab091bf1c.wav",
      "word": [
        {
          "ab": "aki",
          "ch": "希望，期許",
          "sound": "https://d2y1wf6g5bpaph.cloudfront.net/files/2025/01/02/6798c7801bfd72ff44a8bfc3e11c4a4a.wav"
        },
        {
          "ab": "cu",
          "ch": "我",
          "sound": "https://d2y1wf6g5bpaph.cloudfront.net/files/2025/01/02/d4cb3813ca1c254ead006ca40b0439d0.wav"
        },
        {
          "ab": "yani",
          "ch": "像是",
          "sound": "https://d2y1wf6g5bpaph.cloudfront.net/files/2025/01/02/74df056ed001c9ab6c0f22e5d8494863.wav"
        },
        {
          "ab": "isu",
          "ch": "你",
          "sound": "https://d2y1wf6g5bpaph.cloudfront.net/files/2025/01/02/c8c2b8e4806d05c343f216d7b40459e8.wav"
        },
        {
          "ab": ",",
          "ch": "",
          "sound": null
        },
        {
          "ab": "babaw nya",
          "ch": "將來",
          "sound": "https://d2y1wf6g5bpaph.cloudfront.net/files/2025/01/02/2f3e4909ce0071338891f6e299e57bad.wav"
        },
        {
          "ab": "ga",
          "ch": "是",
          "sound": "https://d2y1wf6g5bpaph.cloudfront.net/files/2025/01/02/d11225de52988f1ac997566915452a34.wav"
        },
        {
          "ab": "mosa",
          "ch": "會；成為",
          "sound": "https://d2y1wf6g5bpaph.cloudfront.net/files/2025/01/02/0544d58c65b05cde6898142f95ad4de3.wav"
        },
        {
          "ab": "cu",
          "ch": "我",
          "sound": "https://d2y1wf6g5bpaph.cloudfront.net/files/2025/01/02/d3527d510feb7924fcbcd3c733545ed7.wav"
        },
        {
          "ab": "galan",
          "ch": "被獲得，被視為",
          "sound": "https://d2y1wf6g5bpaph.cloudfront.net/files/2025/01/02/4ef1830e8ed513b6733808be56492598.wav"
        },
        {
          "ab": "myasa",
          "ch": "優秀，好",
          "sound": "https://d2y1wf6g5bpaph.cloudfront.net/files/2025/01/02/d5c37d19f359edef8ea54865c2ecc2c2.wav"
        },
        {
          "ab": "ci",
          "ch": "很，非常",
          "sound": "https://d2y1wf6g5bpaph.cloudfront.net/files/2025/01/02/04e460e6cb4ca894948677337a90e5ac.wav"
        },
        {
          "ab": "psba biru",
          "ch": "老師",
          "sound": "https://d2y1wf6g5bpaph.cloudfront.net/files/2025/01/02/67d30a7c07431e665281712c2165c084.wav"
        },
        {
          "ab": ".",
          "ch": "",
          "sound": null
        }
      ]
    }
  ]
}