{
  "title": "Balikuan",
  "titleCh": "蝴蝶",
  "soundPath": null,
  "sentence": [
    {
      "chinese": "蝴蝶真美麗。",
      "ab": "Balikuan hai tutuza tu manau’uaz daingaz.",
      "order": "1",
      "sound": "https://d2y1wf6g5bpaph.cloudfront.net/sound/2019/07/11/a8b8ffcaf94679d9d5c8ade0eaa6b7c2.wav",
      "word": [
        {
          "ab": "Balikuan",
          "ch": "蝴蝶",
          "sound": "https://d2y1wf6g5bpaph.cloudfront.net/sound/2019/07/11/38bdcb68a7fb779e848def740068e88b.wav"
        },
        {
          "ab": "hai",
          "ch": "[虛]",
          "sound": "https://d2y1wf6g5bpaph.cloudfront.net/sound/2019/07/11/66625345511d33c20d42a9efc5e96b89.wav"
        },
        {
          "ab": "tutuza",
          "ch": "真的",
          "sound": "https://d2y1wf6g5bpaph.cloudfront.net/sound/2019/07/11/18b397e46ae58ed9cb577ee30e97d718.wav"
        },
        {
          "ab": "tu",
          "ch": "[連]",
          "sound": "https://d2y1wf6g5bpaph.cloudfront.net/sound/2019/07/11/dff3db13c2ab1b70fab91d256ff77c68.wav"
        },
        {
          "ab": "manau’uaz",
          "ch": "美麗",
          "sound": "https://d2y1wf6g5bpaph.cloudfront.net/sound/2019/07/11/2580207c328d1b16796b3eda7612bbba.wav"
        },
        {
          "ab": "daingaz",
          "ch": "非常",
          "sound": "https://d2y1wf6g5bpaph.cloudfront.net/sound/2019/07/11/16f16434728953cfa34fceb1e63dae59.wav"
        },
        {
          "ab": ".",
          "ch": "",
          "sound": null
        }
      ]
    },
    {
      "chinese": "它原來是一隻毛毛蟲，",
      "ab": "Mai’uni nai’ia ha’hap’hap,",
      "order": "2",
      "sound": "https://d2y1wf6g5bpaph.cloudfront.net/sound/2019/07/11/7b2e9a7acb695fed27b8cf4e15d55a13.wav",
      "word": [
        {
          "ab": "Mai’uni",
          "ch": "原來",
          "sound": "https://d2y1wf6g5bpaph.cloudfront.net/sound/2019/07/11/924ff56167d5f329ae9de1fd31dd53c8.wav"
        },
        {
          "ab": "nai’ia",
          "ch": "牠們",
          "sound": "https://d2y1wf6g5bpaph.cloudfront.net/sound/2019/07/11/9ed832a84f8d150a318119c521b8a12d.wav"
        },
        {
          "ab": "ha’hap’hap",
          "ch": "毛毛蟲",
          "sound": "https://d2y1wf6g5bpaph.cloudfront.net/sound/2019/07/11/8470d1b6b5f04c8b71b0eaa693dd7005.wav"
        },
        {
          "ab": ",",
          "ch": "",
          "sound": null
        }
      ]
    },
    {
      "chinese": "現在牠穿著美麗的衣服，",
      "ab": "painukanin naia laupaku mas manau’uaz tu ulus,",
      "order": "3",
      "sound": "https://d2y1wf6g5bpaph.cloudfront.net/sound/2019/07/11/2bc0d226efd6a32921335383525501d2.wav",
      "word": [
        {
          "ab": "painukanin",
          "ch": "穿著",
          "sound": "https://d2y1wf6g5bpaph.cloudfront.net/sound/2019/07/11/d75c1332ad91241040bff3293f1e983a.wav"
        },
        {
          "ab": "naia",
          "ch": "牠們",
          "sound": "https://d2y1wf6g5bpaph.cloudfront.net/sound/2019/07/11/72da0ca19a60e7255fb5ef01bddfe64b.wav"
        },
        {
          "ab": "laupaku",
          "ch": "現在",
          "sound": "https://d2y1wf6g5bpaph.cloudfront.net/sound/2019/07/11/7a9b9fc48697d152a0c387128bc655c7.wav"
        },
        {
          "ab": "mas",
          "ch": "[斜]",
          "sound": "https://d2y1wf6g5bpaph.cloudfront.net/sound/2019/07/11/83194adf540c8dc0e65a1df415599ab0.wav"
        },
        {
          "ab": "manau’uaz",
          "ch": "美麗",
          "sound": "https://d2y1wf6g5bpaph.cloudfront.net/sound/2019/07/11/d06708afee421f7ee3cc51ce3ca9fe53.wav"
        },
        {
          "ab": "tu",
          "ch": "[連]",
          "sound": "https://d2y1wf6g5bpaph.cloudfront.net/sound/2019/07/11/6795c199198518896e5e316410906fc5.wav"
        },
        {
          "ab": "ulus",
          "ch": "衣服",
          "sound": "https://d2y1wf6g5bpaph.cloudfront.net/sound/2019/07/11/e3e990fab114534fe6136132144dbaf4.wav"
        },
        {
          "ab": ",",
          "ch": "",
          "sound": null
        }
      ]
    },
    {
      "chinese": "在花叢裡飛來飛去。",
      "ab": "kusbabai sia masulipuahan tu dangian.",
      "order": "4",
      "sound": "https://d2y1wf6g5bpaph.cloudfront.net/sound/2019/07/11/ae2abbb05d4185268eb27b23c6ba59c8.wav",
      "word": [
        {
          "ab": "kusbabai",
          "ch": "飛來飛去",
          "sound": "https://d2y1wf6g5bpaph.cloudfront.net/sound/2019/07/11/5ce181d2f10f3da3c460b14e9e64006d.wav"
        },
        {
          "ab": "sia",
          "ch": "在",
          "sound": "https://d2y1wf6g5bpaph.cloudfront.net/sound/2019/07/11/7c6df2e29a6d6ff02ee497c8dc5fda42.wav"
        },
        {
          "ab": "masulipuahan",
          "ch": "花叢裡",
          "sound": "https://d2y1wf6g5bpaph.cloudfront.net/sound/2019/07/11/bc03f4945eb10e462070e15f196db875.wav"
        },
        {
          "ab": "tu",
          "ch": "[連]",
          "sound": "https://d2y1wf6g5bpaph.cloudfront.net/sound/2019/07/11/6c8c68e218a53061121d606a9031a1d8.wav"
        },
        {
          "ab": "dangian",
          "ch": "地方",
          "sound": "https://d2y1wf6g5bpaph.cloudfront.net/sound/2019/07/11/dab24bc3a87bd6e688a12867fc3da2c2.wav"
        },
        {
          "ab": ".",
          "ch": "",
          "sound": "https://d2y1wf6g5bpaph.cloudfront.net/sound/2019/07/03/3430a5229f84490455b401320f906bbc.wav"
        }
      ]
    },
    {
      "chinese": "小心，別掉進那蜘蛛網裡。",
      "ab": "Mananulua, katu panangadah sia katukatu cia.",
      "order": "5",
      "sound": "https://d2y1wf6g5bpaph.cloudfront.net/sound/2019/07/11/01cbe0a37741129392d6e8a2838e3f0e.wav",
      "word": [
        {
          "ab": "Mananulua",
          "ch": "要小心",
          "sound": "https://d2y1wf6g5bpaph.cloudfront.net/sound/2019/07/11/065a3ff194a43db20996f1ea8a6cffc8.wav"
        },
        {
          "ab": ",",
          "ch": "",
          "sound": "https://d2y1wf6g5bpaph.cloudfront.net/sound/2019/07/03/12f859247d69c34865d727da522d80ed.wav"
        },
        {
          "ab": "katu",
          "ch": "不要",
          "sound": "https://d2y1wf6g5bpaph.cloudfront.net/sound/2019/07/11/6db13f8d3291b5e2c0c33a953c3d984c.wav"
        },
        {
          "ab": "panangadah",
          "ch": "掉進",
          "sound": "https://d2y1wf6g5bpaph.cloudfront.net/sound/2019/07/11/cd3976bfba2576fe00064d4d3e8eafaa.wav"
        },
        {
          "ab": "sia",
          "ch": "在",
          "sound": "https://d2y1wf6g5bpaph.cloudfront.net/sound/2019/07/11/224fead06ff57b9b662ca82fbf9613d8.wav"
        },
        {
          "ab": "katukatu",
          "ch": "蜘蛛的",
          "sound": "https://d2y1wf6g5bpaph.cloudfront.net/sound/2019/07/11/fd75343e445555fbfce0110bfb9f7952.wav"
        },
        {
          "ab": "cia",
          "ch": "[位]",
          "sound": "https://d2y1wf6g5bpaph.cloudfront.net/sound/2019/07/11/053c529ed37415c4f1967bcd4d24ef5f.wav"
        },
        {
          "ab": ".",
          "ch": "",
          "sound": null
        }
      ]
    }
  ]
}